{"otherData": {},"traceEvents":[{"cat":"function","dur":224311,"name":"glfwInit","ph":"X","pid":0,"tid":2043090548,"ts":35627267241},{"cat":"function","dur":1451596,"name":"glfwCreateWindow","ph":"X","pid":0,"tid":2043090548,"ts":35627491837},{"cat":"function","dur":26037,"name":"void __cdecl Infinite::OpenGLContext::Init(void)","ph":"X","pid":0,"tid":2043090548,"ts":35628943584},{"cat":"function","dur":54,"name":"void __cdecl Infinite::WindowsWindow::SetVSync(bool)","ph":"X","pid":0,"tid":2043090548,"ts":35628969737},{"cat":"function","dur":1705354,"name":"__cdecl Infinite::WindowsWindow::WindowsWindow(const struct Infinite::WindowProps &)","ph":"X","pid":0,"tid":2043090548,"ts":35627264525},{"cat":"function","dur":47,"name":"void __cdecl Infinite::OpenGLRendererAPI::Init(void)","ph":"X","pid":0,"tid":2043090548,"ts":35628969957},{"cat":"function","dur":5,"name":"__cdecl Infinite::OpenGLVertexArray::OpenGLVertexArray(void)","ph":"X","pid":0,"tid":2043090548,"ts":35628970107},{"cat":"function","dur":557,"name":"__cdecl Infinite::OpenGLVertexBuffer::OpenGLVertexBuffer(float *,unsigned int)","ph":"X","pid":0,"tid":2043090548,"ts":35628970181},{"cat":"function","dur":2,"name":"void __cdecl Infinite::OpenGLVertexBuffer::Bind(void) const","ph":"X","pid":0,"tid":2043090548,"ts":35628970907},{"cat":"function","dur":72,"name":"void __cdecl Infinite::OpenGLVertexArray::AddVertexBuffer(const class std::shared_ptr<class Infinite::VertexBuffer> &)","ph":"X","pid":0,"tid":2043090548,"ts":35628970900},{"cat":"function","dur":18,"name":"__cdecl Infinite::OpenGLIndexBuffer::OpenGLIndexBuffer(unsigned int *,unsigned int)","ph":"X","pid":0,"tid":2043090548,"ts":35628971023},{"cat":"function","dur":0,"name":"void __cdecl Infinite::OpenGLIndexBuffer::Bind(void) const","ph":"X","pid":0,"tid":2043090548,"ts":35628971097},{"cat":"function","dur":52,"name":"void __cdecl Infinite::OpenGLVertexArray::SetIndexBuffer(const class std::shared_ptr<class Infinite::IndexBuffer> &)","ph":"X","pid":0,"tid":2043090548,"ts":35628971094},{"cat":"function","dur":333,"name":"__cdecl Infinite::OpenGLTexture2D::OpenGLTexture2D(unsigned int,unsigned int)","ph":"X","pid":0,"tid":2043090548,"ts":35628971208},{"cat":"function","dur":98,"name":"void __cdecl Infinite::OpenGLTexture2D::SetData(void *,unsigned int)","ph":"X","pid":0,"tid":2043090548,"ts":35628971623},{"cat":"function","dur":429,"name":"class std::basic_string<char,struct std::char_traits<char>,class std::allocator<char> > __cdecl Infinite::OpenGLShader::ReadFile(const class std::basic_string<char,struct std::char_traits<char>,class std::allocator<char> > &)","ph":"X","pid":0,"tid":2043090548,"ts":35628971812},{"cat":"function","dur":76,"name":"class std::unordered_map<unsigned int,class std::basic_string<char,struct std::char_traits<char>,class std::allocator<char> >,struct std::hash<unsigned int>,struct std::equal_to<unsigned int>,class std::allocator<struct std::pair<unsigned int const ,class std::basic_string<char,struct std::char_traits<char>,class std::allocator<char> > > > > __cdecl Infinite::OpenGLShader::PreProcess(const class std::basic_string<char,struct std::char_traits<char>,class std::allocator<char> > &)","ph":"X","pid":0,"tid":2043090548,"ts":35628972328},{"cat":"function","dur":548,"name":"void __cdecl Infinite::OpenGLShader::Compile(const class std::unordered_map<unsigned int,class std::basic_string<char,struct std::char_traits<char>,class std::allocator<char> >,struct std::hash<unsigned int>,struct std::equal_to<unsigned int>,class std::allocator<struct std::pair<unsigned int const ,class std::basic_string<char,struct std::char_traits<char>,class std::allocator<char> > > > > &)","ph":"X","pid":0,"tid":2043090548,"ts":35628972483},{"cat":"function","dur":1315,"name":"__cdecl Infinite::OpenGLShader::OpenGLShader(const class std::basic_string<char,struct std::char_traits<char>,class std::allocator<char> > &)","ph":"X","pid":0,"tid":2043090548,"ts":35628971806},{"cat":"function","dur":14,"name":"void __cdecl Infinite::OpenGLShader::Bind(void) const","ph":"X","pid":0,"tid":2043090548,"ts":35628973175},{"cat":"function","dur":14,"name":"void __cdecl Infinite::OpenGLShader::SetInt(const class std::basic_string<char,struct std::char_traits<char>,class std::allocator<char> > &,int)","ph":"X","pid":0,"tid":2043090548,"ts":35628973306},{"cat":"function","dur":3288,"name":"void __cdecl Infinite::Renderer2D::Init(void)","ph":"X","pid":0,"tid":2043090548,"ts":35628970090},{"cat":"function","dur":3483,"name":"void __cdecl Infinite::Renderer::Init(void)","ph":"X","pid":0,"tid":2043090548,"ts":35628969951},{"cat":"function","dur":330,"name":"void __cdecl Infinite::ImGuiLayer::OnAttach(void)","ph":"X","pid":0,"tid":2043090548,"ts":35628973517},{"cat":"function","dur":422,"name":"void __cdecl Infinite::Application::PushOverlay(class Infinite::Layer *)","ph":"X","pid":0,"tid":2043090548,"ts":35628973502},{"cat":"function","dur":1709509,"name":"__cdecl Infinite::Application::Application(void)","ph":"X","pid":0,"tid":2043090548,"ts":35627264492},{"cat":"function","dur":4,"name":"__cdecl Infinite::OrthographicCamera::OrthographicCamera(float,float,float,float)","ph":"X","pid":0,"tid":2043090548,"ts":35628974073},{"cat":"function","dur":489,"name":"stbi_load - OpenGLTexture2D::OpenGLTexture2D(const std:string&)","ph":"X","pid":0,"tid":2043090548,"ts":35628974139},{"cat":"function","dur":1238,"name":"__cdecl Infinite::OpenGLTexture2D::OpenGLTexture2D(const class std::basic_string<char,struct std::char_traits<char>,class std::allocator<char> > &)","ph":"X","pid":0,"tid":2043090548,"ts":35628974139},{"cat":"function","dur":1397,"name":"void __cdecl Sandbox2D::OnAttach(void)","ph":"X","pid":0,"tid":2043090548,"ts":35628974134},{"cat":"function","dur":1453,"name":"void __cdecl Infinite::Application::PushLayer(class Infinite::Layer *)","ph":"X","pid":0,"tid":2043090548,"ts":35628974129}]}